{"GeneratedAt":"2026-07-16 20:47","TotalContacts":50,"UniqueCompanies":[{"Company":"삼성SDS","Industry":"컴퓨터 프로그래밍, 시스템 통합 및 관리업","ContactCount":5,"DueContactCount":3},{"Company":"LG CNS","Industry":"컴퓨터 프로그래밍, 시스템 통합 및 관리업","ContactCount":5,"DueContactCount":3},{"Company":"SK C&C","Industry":"시스템 소프트웨어 개발 및 공급업","ContactCount":5,"DueContactCount":4},{"Company":"포스코DX","Industry":"컴퓨터 프로그래밍, 시스템 통합 및 관리업","ContactCount":5,"DueContactCount":3},{"Company":"현대오토에버","Industry":"컴퓨터 프로그래밍, 시스템 통합 및 관리업","ContactCount":5,"DueContactCount":4},{"Company":"신세계I&C","Industry":"컴퓨터 프로그래밍, 시스템 통합 및 관리업","ContactCount":5,"DueContactCount":4},{"Company":"롯데정보통신","Industry":"컴퓨터 프로그래밍, 시스템 통합 및 관리업","ContactCount":5,"DueContactCount":5},{"Company":"한화시스템","Industry":"컴퓨터 프로그래밍, 시스템 통합 및 관리업","ContactCount":5,"DueContactCount":5},{"Company":"CJ올리브네트웍스","Industry":"컴퓨터 프로그래밍, 시스템 통합 및 관리업","ContactCount":5,"DueContactCount":4},{"Company":"아시아나IDT","Industry":"컴퓨터 프로그래밍, 시스템 통합 및 관리업","ContactCount":5,"DueContactCount":5}],"Contacts":[{"No":1,"Company":"삼성SDS","Name":"최**","Title":"과장","Email":"k******@samsung.com","Phone":"031-****-4001","Industry":"컴퓨터 프로그래밍, 시스템 통합 및 관리업","LastContact":"2025-08-16","DaysSinceContact":335,"IsDue":true},{"No":2,"Company":"LG CNS","Name":"조**","Title":"부장","Email":"c*****@lgcns.com","Phone":"02-****-6002","Industry":"컴퓨터 프로그래밍, 시스템 통합 및 관리업","LastContact":"2026-05-13","DaysSinceContact":65,"IsDue":true},{"No":3,"Company":"SK C&C","Name":"임**","Title":"책임연구원","Email":"y*****@sk.com","Phone":"02-****-2003","Industry":"시스템 소프트웨어 개발 및 공급업","LastContact":"2026-06-27","DaysSinceContact":20,"IsDue":false},{"No":4,"Company":"포스코DX","Name":"서**","Title":"프로","Email":"m*******@poscodx.com","Phone":"031-****-4004","Industry":"컴퓨터 프로그래밍, 시스템 통합 및 관리업","LastContact":"2026-02-19","DaysSinceContact":148,"IsDue":true},{"No":5,"Company":"현대오토에버","Name":"황**","Title":"사원","Email":"m*******@hyundai-autoever.com","Phone":"02-****-6005","Industry":"컴퓨터 프로그래밍, 시스템 통합 및 관리업","LastContact":"2026-03-06","DaysSinceContact":133,"IsDue":true},{"No":6,"Company":"신세계I&C","Name":"전**","Title":"과장","Email":"m*******@shinsegae-inc.com","Phone":"02-****-2006","Industry":"컴퓨터 프로그래밍, 시스템 통합 및 관리업","LastContact":"2026-03-17","DaysSinceContact":122,"IsDue":true},{"No":7,"Company":"롯데정보통신","Name":"이**","Title":"부장","Email":"m*******@ldcc.co.kr","Phone":"031-****-4007","Industry":"컴퓨터 프로그래밍, 시스템 통합 및 관리업","LastContact":"2026-04-29","DaysSinceContact":79,"IsDue":true},{"No":8,"Company":"한화시스템","Name":"정**","Title":"책임연구원","Email":"m*******@hanwha.com","Phone":"02-****-6008","Industry":"컴퓨터 프로그래밍, 시스템 통합 및 관리업","LastContact":"2026-05-18","DaysSinceContact":60,"IsDue":true},{"No":9,"Company":"CJ올리브네트웍스","Name":"윤**","Title":"프로","Email":"m*******@cj.net","Phone":"02-****-2009","Industry":"컴퓨터 프로그래밍, 시스템 통합 및 관리업","LastContact":"2025-07-28","DaysSinceContact":354,"IsDue":true},{"No":10,"Company":"아시아나IDT","Name":"한**","Title":"사원","Email":"m********@asianaidt.com","Phone":"031-****-4010","Industry":"컴퓨터 프로그래밍, 시스템 통합 및 관리업","LastContact":"2025-10-03","DaysSinceContact":287,"IsDue":true},{"No":11,"Company":"삼성SDS","Name":"신**","Title":"과장","Email":"m********@samsung.com","Phone":"02-****-6011","Industry":"컴퓨터 프로그래밍, 시스템 통합 및 관리업","LastContact":"2026-05-26","DaysSinceContact":52,"IsDue":false},{"No":12,"Company":"LG CNS","Name":"안**","Title":"부장","Email":"m********@lgcns.com","Phone":"02-****-2012","Industry":"컴퓨터 프로그래밍, 시스템 통합 및 관리업","LastContact":"2025-09-10","DaysSinceContact":310,"IsDue":true},{"No":13,"Company":"SK C&C","Name":"홍**","Title":"책임연구원","Email":"m********@sk.com","Phone":"031-****-4013","Industry":"시스템 소프트웨어 개발 및 공급업","LastContact":"2025-12-05","DaysSinceContact":224,"IsDue":true},{"No":14,"Company":"포스코DX","Name":"박**","Title":"프로","Email":"m********@poscodx.com","Phone":"02-****-6014","Industry":"컴퓨터 프로그래밍, 시스템 통합 및 관리업","LastContact":"2026-06-23","DaysSinceContact":24,"IsDue":false},{"No":15,"Company":"현대오토에버","Name":"강**","Title":"사원","Email":"m********@hyundai-autoever.com","Phone":"02-****-2015","Industry":"컴퓨터 프로그래밍, 시스템 통합 및 관리업","LastContact":"2026-06-24","DaysSinceContact":23,"IsDue":false},{"No":16,"Company":"신세계I&C","Name":"장**","Title":"과장","Email":"m********@shinsegae-inc.com","Phone":"031-****-4016","Industry":"컴퓨터 프로그래밍, 시스템 통합 및 관리업","LastContact":"2026-05-23","DaysSinceContact":55,"IsDue":false},{"No":17,"Company":"롯데정보통신","Name":"오**","Title":"부장","Email":"m********@ldcc.co.kr","Phone":"02-****-6017","Industry":"컴퓨터 프로그래밍, 시스템 통합 및 관리업","LastContact":"2026-03-20","DaysSinceContact":119,"IsDue":true},{"No":18,"Company":"한화시스템","Name":"권**","Title":"책임연구원","Email":"m********@hanwha.com","Phone":"02-****-2018","Industry":"컴퓨터 프로그래밍, 시스템 통합 및 관리업","LastContact":"2026-03-12","DaysSinceContact":127,"IsDue":true},{"No":19,"Company":"CJ올리브네트웍스","Name":"송**","Title":"프로","Email":"m********@cj.net","Phone":"031-****-4019","Industry":"컴퓨터 프로그래밍, 시스템 통합 및 관리업","LastContact":"2025-10-24","DaysSinceContact":266,"IsDue":true},{"No":20,"Company":"아시아나IDT","Name":"김**","Title":"사원","Email":"m********@asianaidt.com","Phone":"02-****-6020","Industry":"컴퓨터 프로그래밍, 시스템 통합 및 관리업","LastContact":"2025-09-04","DaysSinceContact":316,"IsDue":true},{"No":21,"Company":"삼성SDS","Name":"최**","Title":"과장","Email":"m********@samsung.com","Phone":"02-****-2021","Industry":"컴퓨터 프로그래밍, 시스템 통합 및 관리업","LastContact":"2026-06-26","DaysSinceContact":21,"IsDue":false},{"No":22,"Company":"LG CNS","Name":"조**","Title":"부장","Email":"m********@lgcns.com","Phone":"031-****-4022","Industry":"컴퓨터 프로그래밍, 시스템 통합 및 관리업","LastContact":"2025-09-25","DaysSinceContact":295,"IsDue":true},{"No":23,"Company":"SK C&C","Name":"임**","Title":"책임연구원","Email":"m********@sk.com","Phone":"02-****-6023","Industry":"시스템 소프트웨어 개발 및 공급업","LastContact":"2026-03-30","DaysSinceContact":109,"IsDue":true},{"No":24,"Company":"포스코DX","Name":"서**","Title":"프로","Email":"m********@poscodx.com","Phone":"02-****-2024","Industry":"컴퓨터 프로그래밍, 시스템 통합 및 관리업","LastContact":"2025-08-11","DaysSinceContact":340,"IsDue":true},{"No":25,"Company":"현대오토에버","Name":"황**","Title":"사원","Email":"m********@hyundai-autoever.com","Phone":"031-****-4025","Industry":"컴퓨터 프로그래밍, 시스템 통합 및 관리업","LastContact":"2025-07-15","DaysSinceContact":367,"IsDue":true},{"No":26,"Company":"신세계I&C","Name":"전**","Title":"과장","Email":"m********@shinsegae-inc.com","Phone":"02-****-6026","Industry":"컴퓨터 프로그래밍, 시스템 통합 및 관리업","LastContact":"2025-10-03","DaysSinceContact":287,"IsDue":true},{"No":27,"Company":"롯데정보통신","Name":"이**","Title":"부장","Email":"m********@ldcc.co.kr","Phone":"02-****-2027","Industry":"컴퓨터 프로그래밍, 시스템 통합 및 관리업","LastContact":"2025-12-07","DaysSinceContact":222,"IsDue":true},{"No":28,"Company":"한화시스템","Name":"정**","Title":"책임연구원","Email":"m********@hanwha.com","Phone":"031-****-4028","Industry":"컴퓨터 프로그래밍, 시스템 통합 및 관리업","LastContact":"2026-03-19","DaysSinceContact":120,"IsDue":true},{"No":29,"Company":"CJ올리브네트웍스","Name":"윤**","Title":"프로","Email":"m********@cj.net","Phone":"02-****-6029","Industry":"컴퓨터 프로그래밍, 시스템 통합 및 관리업","LastContact":"2025-11-22","DaysSinceContact":237,"IsDue":true},{"No":30,"Company":"아시아나IDT","Name":"한**","Title":"사원","Email":"m********@asianaidt.com","Phone":"02-****-2030","Industry":"컴퓨터 프로그래밍, 시스템 통합 및 관리업","LastContact":"2025-09-11","DaysSinceContact":309,"IsDue":true},{"No":31,"Company":"삼성SDS","Name":"신**","Title":"과장","Email":"m********@samsung.com","Phone":"031-****-4031","Industry":"컴퓨터 프로그래밍, 시스템 통합 및 관리업","LastContact":"2026-02-17","DaysSinceContact":150,"IsDue":true},{"No":32,"Company":"LG CNS","Name":"안**","Title":"부장","Email":"m********@lgcns.com","Phone":"02-****-6032","Industry":"컴퓨터 프로그래밍, 시스템 통합 및 관리업","LastContact":"2026-07-06","DaysSinceContact":11,"IsDue":false},{"No":33,"Company":"SK C&C","Name":"홍**","Title":"책임연구원","Email":"m********@sk.com","Phone":"02-****-2033","Industry":"시스템 소프트웨어 개발 및 공급업","LastContact":"2026-04-19","DaysSinceContact":89,"IsDue":true},{"No":34,"Company":"포스코DX","Name":"박**","Title":"프로","Email":"m********@poscodx.com","Phone":"031-****-4034","Industry":"컴퓨터 프로그래밍, 시스템 통합 및 관리업","LastContact":"2025-07-17","DaysSinceContact":365,"IsDue":true},{"No":35,"Company":"현대오토에버","Name":"강**","Title":"사원","Email":"m********@hyundai-autoever.com","Phone":"02-****-6035","Industry":"컴퓨터 프로그래밍, 시스템 통합 및 관리업","LastContact":"2025-12-05","DaysSinceContact":224,"IsDue":true},{"No":36,"Company":"신세계I&C","Name":"장**","Title":"과장","Email":"m********@shinsegae-inc.com","Phone":"02-****-2036","Industry":"컴퓨터 프로그래밍, 시스템 통합 및 관리업","LastContact":"2026-01-16","DaysSinceContact":182,"IsDue":true},{"No":37,"Company":"롯데정보통신","Name":"오**","Title":"부장","Email":"m********@ldcc.co.kr","Phone":"031-****-4037","Industry":"컴퓨터 프로그래밍, 시스템 통합 및 관리업","LastContact":"2026-02-17","DaysSinceContact":150,"IsDue":true},{"No":38,"Company":"한화시스템","Name":"권**","Title":"책임연구원","Email":"m********@hanwha.com","Phone":"02-****-6038","Industry":"컴퓨터 프로그래밍, 시스템 통합 및 관리업","LastContact":"2026-04-21","DaysSinceContact":87,"IsDue":true},{"No":39,"Company":"CJ올리브네트웍스","Name":"송**","Title":"프로","Email":"m********@cj.net","Phone":"02-****-2039","Industry":"컴퓨터 프로그래밍, 시스템 통합 및 관리업","LastContact":"2026-03-21","DaysSinceContact":118,"IsDue":true},{"No":40,"Company":"아시아나IDT","Name":"김**","Title":"사원","Email":"m********@asianaidt.com","Phone":"031-****-4040","Industry":"컴퓨터 프로그래밍, 시스템 통합 및 관리업","LastContact":"2026-01-18","DaysSinceContact":180,"IsDue":true},{"No":41,"Company":"삼성SDS","Name":"최**","Title":"과장","Email":"m********@samsung.com","Phone":"02-****-6041","Industry":"컴퓨터 프로그래밍, 시스템 통합 및 관리업","LastContact":"2026-05-18","DaysSinceContact":60,"IsDue":true},{"No":42,"Company":"LG CNS","Name":"조**","Title":"부장","Email":"m********@lgcns.com","Phone":"02-****-2042","Industry":"컴퓨터 프로그래밍, 시스템 통합 및 관리업","LastContact":"2026-05-23","DaysSinceContact":55,"IsDue":false},{"No":43,"Company":"SK C&C","Name":"임**","Title":"책임연구원","Email":"m********@sk.com","Phone":"031-****-4043","Industry":"시스템 소프트웨어 개발 및 공급업","LastContact":"2025-12-27","DaysSinceContact":202,"IsDue":true},{"No":44,"Company":"포스코DX","Name":"서**","Title":"프로","Email":"m********@poscodx.com","Phone":"02-****-6044","Industry":"컴퓨터 프로그래밍, 시스템 통합 및 관리업","LastContact":"2026-05-21","DaysSinceContact":57,"IsDue":false},{"No":45,"Company":"현대오토에버","Name":"황**","Title":"사원","Email":"m********@hyundai-autoever.com","Phone":"02-****-2045","Industry":"컴퓨터 프로그래밍, 시스템 통합 및 관리업","LastContact":"2026-01-07","DaysSinceContact":191,"IsDue":true},{"No":46,"Company":"신세계I&C","Name":"전**","Title":"과장","Email":"m********@shinsegae-inc.com","Phone":"031-****-4046","Industry":"컴퓨터 프로그래밍, 시스템 통합 및 관리업","LastContact":"2026-01-14","DaysSinceContact":184,"IsDue":true},{"No":47,"Company":"롯데정보통신","Name":"이**","Title":"부장","Email":"m********@ldcc.co.kr","Phone":"02-****-6047","Industry":"컴퓨터 프로그래밍, 시스템 통합 및 관리업","LastContact":"2025-09-03","DaysSinceContact":317,"IsDue":true},{"No":48,"Company":"한화시스템","Name":"정**","Title":"책임연구원","Email":"m********@hanwha.com","Phone":"02-****-2048","Industry":"컴퓨터 프로그래밍, 시스템 통합 및 관리업","LastContact":"2026-02-24","DaysSinceContact":143,"IsDue":true},{"No":49,"Company":"CJ올리브네트웍스","Name":"윤**","Title":"프로","Email":"m********@cj.net","Phone":"031-****-4049","Industry":"컴퓨터 프로그래밍, 시스템 통합 및 관리업","LastContact":"2026-06-17","DaysSinceContact":30,"IsDue":false},{"No":50,"Company":"아시아나IDT","Name":"한**","Title":"사원","Email":"m********@asianaidt.com","Phone":"02-****-6050","Industry":"컴퓨터 프로그래밍, 시스템 통합 및 관리업","LastContact":"2025-11-16","DaysSinceContact":243,"IsDue":true}]}